{"Jira": "\n<a href=https://jira.corp.inmobi.com:8443/browse/NOC-123>NOC-123</a>\n", "Status": "resolved", "Slack": "\n<a href=https://inmobi.slack.com/messages/noc-123>noc-123</a>\n", "Downtime": "\n<p style='color:red'><b>Status:</b>RED</p>\n", "Summary": ["<ul><li>Hello Testing</li></ul>", "<ul><li>New updates</li></ul>", "<ul><li>Dome</li></ul>"], "Time": "14:53 PM", "Date": "15-December-2016", "Buisness Impacted": "NA", "Issue": "S1 Outage Communication Final Testing ", "Region Impacted": "noc", "Application Impacted": "noc"}